[
    {
        "title": "Elshad Mirbashir oghlu",
        "revid": 1194162044,
        "prediction": "C"
    },
    {
        "title": "Tahir Mirkishili",
        "revid": 1210593900,
        "prediction": "Start"
    },
    {
        "title": "Movsum Samadov",
        "revid": 1241255046,
        "prediction": "C"
    },
    {
        "title": "Fuad Naghiyev",
        "revid": 1248662296,
        "prediction": "Start"
    },
    {
        "title": "Eldar Namazov",
        "revid": 1206211739,
        "prediction": "Start"
    },
    {
        "title": "Namig Nasrullayev",
        "revid": 1158375491,
        "prediction": "Stub"
    },
    {
        "title": "Siyavush Novruzov",
        "revid": 1243520070,
        "prediction": "C"
    },
    {
        "title": "Zahid Oruj",
        "revid": 1213965350,
        "prediction": "Start"
    },
    {
        "title": "Sadig Rahimov",
        "revid": 1245157534,
        "prediction": "C"
    },
    {
        "title": "Suleyman Rahimov",
        "revid": 1193027962,
        "prediction": "C"
    },
    {
        "title": "Huseyn Rahmanov",
        "revid": 1106104383,
        "prediction": "Stub"
    },
    {
        "title": "Rovshen Rzayev",
        "revid": 1208078338,
        "prediction": "Start"
    },
    {
        "title": "Hasan Seyidov",
        "revid": 1148385245,
        "prediction": "Stub"
    },
    {
        "title": "Hasan Seyidov (scientist)",
        "revid": 1198202282,
        "prediction": "Start"
    },
    {
        "title": "Parviz Shahbazov",
        "revid": 1213858589,
        "prediction": "Start"
    },
    {
        "title": "Mammad agha Shahtakhtinski",
        "revid": 1185599926,
        "prediction": "C"
    },
    {
        "title": "Abid Sharifov",
        "revid": 1243510547,
        "prediction": "Start"
    },
    {
        "title": "Shirali Akhundov",
        "revid": 1213002608,
        "prediction": "C"
    },
    {
        "title": "Ikhtiyar Shirinov",
        "revid": 1243510572,
        "prediction": "Stub"
    },
    {
        "title": "Bakhtiyar Vahabzadeh",
        "revid": 1249675761,
        "prediction": "C"
    },
    {
        "title": "Vugar Mustafayev (minister)",
        "revid": 1208077047,
        "prediction": "Start"
    },
    {
        "title": "Yusif Ziya Talibzadeh",
        "revid": 1243510546,
        "prediction": "GA"
    },
    {
        "title": "Nurali Yusifbayli",
        "revid": 1243510541,
        "prediction": "Start"
    },
    {
        "title": "Keith Bell (Bahamian politician)",
        "revid": 1243023554,
        "prediction": "Start"
    },
    {
        "title": "Charles Carter (Bahamian journalist)",
        "revid": 1162793449,
        "prediction": "C"
    },
    {
        "title": "Harold Christie",
        "revid": 1142294843,
        "prediction": "Start"
    },
    {
        "title": "Timothy Donaldson",
        "revid": 1245586658,
        "prediction": "C"
    },
    {
        "title": "Eugene Dupuch",
        "revid": 1181612386,
        "prediction": "Start"
    },
    {
        "title": "Joseph Robert Love",
        "revid": 1177467150,
        "prediction": "C"
    },
    {
        "title": "McKell Bonaby",
        "revid": 1238577650,
        "prediction": "Stub"
    },
    {
        "title": "Pakesia Parker-Edgecombe",
        "revid": 1226025677,
        "prediction": "Start"
    },
    {
        "title": "James Carmichael Smith (postmaster)",
        "revid": 1248344476,
        "prediction": "C"
    },
    {
        "title": "Mohammed Isa Al Abbasi",
        "revid": 1171757402,
        "prediction": "Stub"
    },
    {
        "title": "Abdulla Adel Fakhro",
        "revid": 1223700072,
        "prediction": "Start"
    },
    {
        "title": "Abdullah bin Isa Al Khalifa",
        "revid": 1182830303,
        "prediction": "Start"
    },
    {
        "title": "Ahmed Behzad (Bahrain)",
        "revid": 1063482737,
        "prediction": "Stub"
    },
    {
        "title": "Kamal Ahmed (politician)",
        "revid": 1215486840,
        "prediction": "Stub"
    },
    {
        "title": "Mohamed Ali Hasan Ali",
        "revid": 1006173162,
        "prediction": "Stub"
    },
    {
        "title": "Khalid Almoayed",
        "revid": 1215466172,
        "prediction": "Stub"
    },
    {
        "title": "Aymen Tawfeeq Almoayed",
        "revid": 1227286508,
        "prediction": "Start"
    },
    {
        "title": "Nazar Al Baharna",
        "revid": 1241906132,
        "prediction": "Start"
    },
    {
        "title": "Mahmood Al Bahrani",
        "revid": 1161492589,
        "prediction": "Stub"
    },
    {
        "title": "Ammar Al Bannai",
        "revid": 1231654401,
        "prediction": "Start"
    },
    {
        "title": "Jawad Fairooz",
        "revid": 1177286981,
        "prediction": "Start"
    },
    {
        "title": "Qasim Fakhro",
        "revid": 1099067663,
        "prediction": "Start"
    },
    {
        "title": "Faisal al-Hamar",
        "revid": 1218302538,
        "prediction": "Stub"
    },
    {
        "title": "Nabeel bin Yaqub Al-Hamar",
        "revid": 1159628135,
        "prediction": "Stub"
    },
    {
        "title": "Isa bin Abdulrahman Al Hammadi",
        "revid": 1098344827,
        "prediction": "Stub"
    },
    {
        "title": "Jameel Humadan",
        "revid": 1148959062,
        "prediction": "Start"
    },
    {
        "title": "Isa bin Ibrahim Al Khalifa",
        "revid": 1146485875,
        "prediction": "Stub"
    }
]